siruta.csv
sirutalib.py
sirutalib-1.3.0.dist-info/METADATA
sirutalib-1.3.0.dist-info/WHEEL
sirutalib-1.3.0.dist-info/top_level.txt
sirutalib-1.3.0.dist-info/RECORD
