Metadata-Version: 2.4
Name: sirutalib
Version: 1.3.0
Summary: Work with the Romanian settlement database, SIRUTA
Home-page: http://proiecte.strainu.ro/siruta/
Author: Andrei Cipu
Author-email: Andrei Cipu <siruta@strainu.ro>
License-Expression: BSD-3-Clause
Requires-Python: >=3.9
Requires-Dist: setuptools>=80.9.0
Dynamic: author
Dynamic: home-page
